pyqt/__init__.py
pyqt/api/__init__.py
pyqt/api/constants.py
pyqt/api/interface.py
pyqt/api/impl/__init__.py
pyqt/api/impl/futu_api.py
pyqt/api/impl/ib_api.py
pyqt/utils/__init__.py
pyqt/utils/time.py
yolo_pyqt-0.1.7.dist-info/LICENSE
yolo_pyqt-0.1.7.dist-info/METADATA
yolo_pyqt-0.1.7.dist-info/WHEEL
yolo_pyqt-0.1.7.dist-info/top_level.txt
yolo_pyqt-0.1.7.dist-info/RECORD
