Metadata-Version: 2.1
Name: yolo-pyqt
Version: 0.1.7
Summary: yolo-pyqt provides an easy way to build automated quantitative trading systems for individual traders.
Home-page: https://github.com/TaoYang526/yolo-pyqt
Author: Tao Yang
Author-email: ytaofighting@gmail.com
License: Apache License 2.0
Keywords: quantitative-trading qt api
Platform: UNKNOWN
Classifier: Development Status :: 2 - Pre-Alpha
Classifier: Topic :: Utilities
Classifier: License :: OSI Approved :: Apache Software License
Classifier: Programming Language :: Python :: 3
License-File: LICENSE
